vsol/__init__.py
vsol-0.0.1.dist-info/METADATA
vsol-0.0.1.dist-info/WHEEL
vsol-0.0.1.dist-info/top_level.txt
vsol-0.0.1.dist-info/RECORD
