Metadata-Version: 2.1
Name: vsol
Version: 0.0.1
Summary: VSOL is a simple, human-readable, and easy-to-use configuration file format.
Home-page: https://github.com/vsol-lang/vsol
Author: Md. Almas Ali
Author-email: almaspr3@gmail.com
License: MIT
Platform: UNKNOWN
Classifier: Development Status :: 1 - Planning
Classifier: Intended Audience :: Developers
Classifier: License :: OSI Approved :: MIT License
Classifier: Natural Language :: English
Classifier: Operating System :: OS Independent
Classifier: Programming Language :: Python :: 3.8
Classifier: Programming Language :: Python :: 3.9
Classifier: Programming Language :: Python :: 3.10
Classifier: Programming Language :: Python :: 3.11
Classifier: Topic :: Software Development :: Libraries :: Python Modules
Classifier: Typing :: Typed
Classifier: Topic :: Utilities
Requires-Python: >=3.8
